{"cameraMode":{"drawMode":0,"name":"Shaded","section":"Shading Mode"},"sceneLighting":false,"audioPlay":false,"sceneViewState":{"m_AlwaysRefresh":false,"showFog":true,"showSkybox":true,"showFlares":true,"showImageEffects":true,"showParticleSystems":true,"showVisualEffectGraphs":true,"m_FxEnabled":true},"in2DMode":false,"pivot":{"x":184.0,"y":460.0,"z":0.0},"rotation":{"x":-0.12297486513853073,"y":-0.01875530742108822,"z":0.0023348110262304546,"w":-0.992235004901886},"size":35.3588752746582,"orthographic":false}